[
  {
    "user": "LadyCherie",
    "wagered": 468678.48,
    "price": 7500
  },
  {
    "user": "CherFolt34",
    "wagered": 403622.88,
    "price": 4000
  },
  {
    "user": "BigZai2601",
    "wagered": 204843.39,
    "price": 2000
  },
  {
    "user": "Mamakote2015",
    "wagered": 174087.97,
    "price": 1400
  },
  {
    "user": "luncini",
    "wagered": 168138.41,
    "price": 1000
  },
  {
    "user": "Jennasiddiqui0",
    "wagered": 161155.17,
    "price": 800
  },
  {
    "user": "XJQKA",
    "wagered": 146930.2,
    "price": 640
  },
  {
    "user": "Ameen409",
    "wagered": 111398.38,
    "price": 480
  },
  {
    "user": "gayatri0613",
    "wagered": 84523.87,
    "price": 400
  },
  {
    "user": "Kmkkk8889",
    "wagered": 74164.02,
    "price": 320
  },
  {
    "user": "85Yotawoman",
    "wagered": 70708.82,
    "price": 280
  },
  {
    "user": "iemace12",
    "wagered": 67217.1,
    "price": 240
  },
  {
    "user": "kapesaumaga",
    "wagered": 59247.29,
    "price": 200
  },
  {
    "user": "Creamysriracha",
    "wagered": 43360.86,
    "price": 140
  },
  {
    "user": "Mamba24810",
    "wagered": 43143.82,
    "price": 100
  },
  {
    "user": "Hmack87",
    "wagered": 42913.97,
    "price": 90
  },
  {
    "user": "doomed4348",
    "wagered": 41889.9,
    "price": 80
  },
  {
    "user": "NEEDTHAWIN",
    "wagered": 38722.37,
    "price": 70
  },
  {
    "user": "kleryyyy",
    "wagered": 35635.64,
    "price": 60
  },
  {
    "user": "KickinsMom",
    "wagered": 34569.47,
    "price": 50
  },
  {
    "user": "JandroCubano",
    "wagered": 31255.82,
    "price": 40
  },
  {
    "user": "Ilovetheskye",
    "wagered": 30573.55,
    "price": 35
  },
  {
    "user": "SweetAndCrazy",
    "wagered": 29913.48,
    "price": 30
  },
  {
    "user": "Irvyne",
    "wagered": 29578.05,
    "price": 25
  },
  {
    "user": "Picklegirl88",
    "wagered": 24960.81,
    "price": 20
  },
  {
    "user": "CL414",
    "wagered": 22896.3,
    "price": 0
  },
  {
    "user": "Yumajin234",
    "wagered": 21183.45,
    "price": 0
  },
  {
    "user": "Akiness",
    "wagered": 20706.04,
    "price": 0
  },
  {
    "user": "Gagelynn",
    "wagered": 20518.87,
    "price": 0
  },
  {
    "user": "Peanutzzz",
    "wagered": 19315.37,
    "price": 0
  },
  {
    "user": "soi",
    "wagered": 19029.01,
    "price": 0
  },
  {
    "user": "Seb2Bet",
    "wagered": 17020.21,
    "price": 0
  },
  {
    "user": "Iskara",
    "wagered": 16135.57,
    "price": 0
  },
  {
    "user": "hezi5",
    "wagered": 16070.47,
    "price": 0
  },
  {
    "user": "Jaysd777",
    "wagered": 15503.56,
    "price": 0
  },
  {
    "user": "Munch5320",
    "wagered": 15174.71,
    "price": 0
  },
  {
    "user": "Bbjornnn",
    "wagered": 14471.27,
    "price": 0
  },
  {
    "user": "VGstakes",
    "wagered": 13669.41,
    "price": 0
  },
  {
    "user": "ShirinMeth",
    "wagered": 13539.99,
    "price": 0
  },
  {
    "user": "wars",
    "wagered": 12567.56,
    "price": 0
  },
  {
    "user": "p0wp0w",
    "wagered": 12394.22,
    "price": 0
  },
  {
    "user": "ceddyboi",
    "wagered": 12392.33,
    "price": 0
  },
  {
    "user": "LLav",
    "wagered": 12227.13,
    "price": 0
  },
  {
    "user": "bigkevssf",
    "wagered": 12214.68,
    "price": 0
  },
  {
    "user": "afanning1",
    "wagered": 12194.14,
    "price": 0
  },
  {
    "user": "horus94978",
    "wagered": 9390.69,
    "price": 0
  },
  {
    "user": "seema123344",
    "wagered": 8616.49,
    "price": 0
  },
  {
    "user": "hulaanmoooo",
    "wagered": 8380.06,
    "price": 0
  },
  {
    "user": "ShinchanPlayz",
    "wagered": 8275.13,
    "price": 0
  },
  {
    "user": "Cottonfam1",
    "wagered": 7920.71,
    "price": 0
  }
]